{"Data":[{"ScheduleForRouteId":6307,"schedulecode":"103/A","scheduleForRouteCode":"5698743","routeCode":"103-D","routeName":"Bhakti Circle - Lal Darwaja","routeDestination":"Lal Darwaja","routeVariant":"NORMAL","firstStopCode":5290,"lastStopCode":4104,"Shift":null,"startTime":"06:35:00","stopTime":"07:50:00","runCode":"103/A","tripSeqNumber":null,"dutyCode":"103/A-F","firstStopName":"Bhakti Circle","lastStopName":"Bhakti Circle","busNo":0},{"ScheduleForRouteId":6308,"schedulecode":"103/B","scheduleForRouteCode":"5698748","routeCode":"103-D","routeName":"Bhakti Circle - Lal Darwaja","routeDestination":"Lal Darwaja","routeVariant":"NORMAL","firstStopCode":5290,"lastStopCode":4104,"Shift":null,"startTime":"08:05:00","stopTime":"09:25:00","runCode":"103/B","tripSeqNumber":null,"dutyCode":"103/B-F","firstStopName":"Bhakti Circle","lastStopName":"Bhakti Circle","busNo":0},{"ScheduleForRouteId":6299,"schedulecode":"103/A","scheduleForRouteCode":"5832393","routeCode":"103-D","routeName":"Bhakti Circle - Lal Darwaja","routeDestination":"Lal Darwaja","routeVariant":"NORMAL","firstStopCode":5290,"lastStopCode":4104,"Shift":null,"startTime":"09:40:00","stopTime":"11:00:00","runCode":"103/A","tripSeqNumber":null,"dutyCode":"103/A-F","firstStopName":"Bhakti Circle","lastStopName":"Bhakti Circle","busNo":0},{"ScheduleForRouteId":6300,"schedulecode":"103/B","scheduleForRouteCode":"5832394","routeCode":"103-D","routeName":"Bhakti Circle - Lal Darwaja","routeDestination":"Lal Darwaja","routeVariant":"NORMAL","firstStopCode":5290,"lastStopCode":4104,"Shift":null,"startTime":"11:20:00","stopTime":"12:40:00","runCode":"103/B","tripSeqNumber":null,"dutyCode":"103/B-F","firstStopName":"Bhakti Circle","lastStopName":"Bhakti Circle","busNo":0},{"ScheduleForRouteId":6304,"schedulecode":"103/A","scheduleForRouteCode":"5832414","routeCode":"103-D","routeName":"Bhakti Circle - Lal Darwaja","routeDestination":"Lal Darwaja","routeVariant":"NORMAL","firstStopCode":5290,"lastStopCode":4104,"Shift":null,"startTime":"15:35:00","stopTime":"17:00:00","runCode":"103/A","tripSeqNumber":null,"dutyCode":"103/A-S","firstStopName":"Bhakti Circle","lastStopName":"Bhakti Circle","busNo":0},{"ScheduleForRouteId":6305,"schedulecode":"103/B","scheduleForRouteCode":"5832491","routeCode":"103-D","routeName":"Bhakti Circle - Lal Darwaja","routeDestination":"Lal Darwaja","routeVariant":"NORMAL","firstStopCode":5290,"lastStopCode":4104,"Shift":null,"startTime":"17:00:00","stopTime":"18:20:00","runCode":"103/B","tripSeqNumber":null,"dutyCode":"103/B-S","firstStopName":"Bhakti Circle","lastStopName":"Bhakti Circle","busNo":0},{"ScheduleForRouteId":6306,"schedulecode":"103/A","scheduleForRouteCode":"5832503","routeCode":"103-D","routeName":"Bhakti Circle - Lal Darwaja","routeDestination":"Lal Darwaja","routeVariant":"NORMAL","firstStopCode":5290,"lastStopCode":4104,"Shift":null,"startTime":"18:20:00","stopTime":"19:35:00","runCode":"103/A","tripSeqNumber":null,"dutyCode":"103/A-S","firstStopName":"Bhakti Circle","lastStopName":"Bhakti Circle","busNo":0},{"ScheduleForRouteId":6301,"schedulecode":"103/B","scheduleForRouteCode":"5832403","routeCode":"103-D","routeName":"Bhakti Circle - Lal Darwaja","routeDestination":"Lal Darwaja","routeVariant":"NORMAL","firstStopCode":5290,"lastStopCode":4104,"Shift":null,"startTime":"19:40:00","stopTime":"20:55:00","runCode":"103/B","tripSeqNumber":null,"dutyCode":"103/B-S","firstStopName":"Bhakti Circle","lastStopName":"Bhakti Circle","busNo":0}],"Paging":{"PageNo":0,"PageSize":2000,"PageCount":1,"TotalRecordCount":8}}