{"Data":[{"ScheduleForRouteId":201,"schedulecode":"123/B","scheduleForRouteCode":"5690579","routeCode":"123-SaS-U","routeName":"Sarangpur Darwaja - Sitarambapa Chowk(Gopal Chowk)","routeDestination":"Sitarambapa Chowk (Gopal Chowk)","routeVariant":"NORMAL","firstStopCode":1204,"lastStopCode":8923,"Shift":null,"startTime":"06:05:00","stopTime":"06:40:00","runCode":"123/B","tripSeqNumber":null,"dutyCode":"123/B-F","firstStopName":"Sarangpur","lastStopName":"Sarangpur","busNo":0},{"ScheduleForRouteId":202,"schedulecode":"123/C","scheduleForRouteCode":"5690580","routeCode":"123-SaS-U","routeName":"Sarangpur Darwaja - Sitarambapa Chowk(Gopal Chowk)","routeDestination":"Sitarambapa Chowk (Gopal Chowk)","routeVariant":"NORMAL","firstStopCode":1204,"lastStopCode":8923,"Shift":null,"startTime":"07:50:00","stopTime":"08:25:00","runCode":"123/C","tripSeqNumber":null,"dutyCode":"123/C-F","firstStopName":"Sarangpur","lastStopName":"Sarangpur","busNo":0}],"Paging":{"PageNo":0,"PageSize":2000,"PageCount":1,"TotalRecordCount":2}}