{"Data":[{"ScheduleForRouteId":236,"schedulecode":"150/L","scheduleForRouteCode":"5690378","routeCode":"150-SC-U","routeName":"Sarangpur Darwaja - Chinubhainagar","routeDestination":"Chinubhainagar","routeVariant":"NORMAL","firstStopCode":1204,"lastStopCode":1819,"Shift":null,"startTime":"05:30:00","stopTime":"06:10:00","runCode":"150/L","tripSeqNumber":null,"dutyCode":"150/L-F","firstStopName":"Sarangpur","lastStopName":"Sarangpur","busNo":0},{"ScheduleForRouteId":228,"schedulecode":"150/M","scheduleForRouteCode":"5690525","routeCode":"150-SC-U","routeName":"Sarangpur Darwaja - Chinubhainagar","routeDestination":"Chinubhainagar","routeVariant":"NORMAL","firstStopCode":1204,"lastStopCode":1819,"Shift":null,"startTime":"05:50:00","stopTime":"06:30:00","runCode":"150/M","tripSeqNumber":null,"dutyCode":"150/M-F","firstStopName":"Sarangpur","lastStopName":"Sarangpur","busNo":0},{"ScheduleForRouteId":133,"schedulecode":"150/N","scheduleForRouteCode":"5697133","routeCode":"150-SC-U","routeName":"Sarangpur Darwaja - Chinubhainagar","routeDestination":"Chinubhainagar","routeVariant":"NORMAL","firstStopCode":1204,"lastStopCode":1819,"Shift":null,"startTime":"06:10:00","stopTime":"06:50:00","runCode":"150/N","tripSeqNumber":null,"dutyCode":"150/N-F","firstStopName":"Sarangpur","lastStopName":"Sarangpur","busNo":0},{"ScheduleForRouteId":134,"schedulecode":"150/O","scheduleForRouteCode":"5697150","routeCode":"150-SC-U","routeName":"Sarangpur Darwaja - Chinubhainagar","routeDestination":"Chinubhainagar","routeVariant":"NORMAL","firstStopCode":1204,"lastStopCode":1819,"Shift":null,"startTime":"06:30:00","stopTime":"07:10:00","runCode":"150/O","tripSeqNumber":null,"dutyCode":"150/O-F","firstStopName":"Sarangpur","lastStopName":"Sarangpur","busNo":0},{"ScheduleForRouteId":70,"schedulecode":"150/Z","scheduleForRouteCode":"5699161","routeCode":"150-SC-U","routeName":"Sarangpur Darwaja - Chinubhainagar","routeDestination":"Chinubhainagar","routeVariant":"NORMAL","firstStopCode":1204,"lastStopCode":1819,"Shift":null,"startTime":"06:40:00","stopTime":"07:20:00","runCode":"150/Z","tripSeqNumber":null,"dutyCode":"150/Z-F","firstStopName":"Sarangpur","lastStopName":"Sarangpur","busNo":0},{"ScheduleForRouteId":135,"schedulecode":"150/P","scheduleForRouteCode":"5697160","routeCode":"150-SC-U","routeName":"Sarangpur Darwaja - Chinubhainagar","routeDestination":"Chinubhainagar","routeVariant":"NORMAL","firstStopCode":1204,"lastStopCode":1819,"Shift":null,"startTime":"06:50:00","stopTime":"07:30:00","runCode":"150/P","tripSeqNumber":null,"dutyCode":"150/P-F","firstStopName":"Sarangpur","lastStopName":"Sarangpur","busNo":0},{"ScheduleForRouteId":123,"schedulecode":"150/Q","scheduleForRouteCode":"5697171","routeCode":"150-SC-U","routeName":"Sarangpur Darwaja - Chinubhainagar","routeDestination":"Chinubhainagar","routeVariant":"NORMAL","firstStopCode":1204,"lastStopCode":1819,"Shift":null,"startTime":"07:10:00","stopTime":"07:50:00","runCode":"150/Q","tripSeqNumber":null,"dutyCode":"150/Q-F","firstStopName":"Sarangpur","lastStopName":"Sarangpur","busNo":0},{"ScheduleForRouteId":71,"schedulecode":"150/Y","scheduleForRouteCode":"5699162","routeCode":"150-SC-U","routeName":"Sarangpur Darwaja - Chinubhainagar","routeDestination":"Chinubhainagar","routeVariant":"NORMAL","firstStopCode":1204,"lastStopCode":1819,"Shift":null,"startTime":"07:20:00","stopTime":"08:00:00","runCode":"150/Y","tripSeqNumber":null,"dutyCode":"150/Y-F","firstStopName":"Sarangpur","lastStopName":"Sarangpur","busNo":0},{"ScheduleForRouteId":178,"schedulecode":"150/R","scheduleForRouteCode":"5692697","routeCode":"150-SC-U","routeName":"Sarangpur Darwaja - Chinubhainagar","routeDestination":"Chinubhainagar","routeVariant":"NORMAL","firstStopCode":1204,"lastStopCode":1819,"Shift":null,"startTime":"07:30:00","stopTime":"08:10:00","runCode":"150/R","tripSeqNumber":null,"dutyCode":"150/R-F","firstStopName":"Sarangpur","lastStopName":"Sarangpur","busNo":0},{"ScheduleForRouteId":179,"schedulecode":"150/S","scheduleForRouteCode":"5692702","routeCode":"150-SC-U","routeName":"Sarangpur Darwaja - Chinubhainagar","routeDestination":"Chinubhainagar","routeVariant":"NORMAL","firstStopCode":1204,"lastStopCode":1819,"Shift":null,"startTime":"07:50:00","stopTime":"08:35:00","runCode":"150/S","tripSeqNumber":null,"dutyCode":"150/S-F","firstStopName":"Sarangpur","lastStopName":"Sarangpur","busNo":0},{"ScheduleForRouteId":181,"schedulecode":"150/T","scheduleForRouteCode":"5692708","routeCode":"150-SC-U","routeName":"Sarangpur Darwaja - Chinubhainagar","routeDestination":"Chinubhainagar","routeVariant":"NORMAL","firstStopCode":1204,"lastStopCode":1819,"Shift":null,"startTime":"08:10:00","stopTime":"08:55:00","runCode":"150/T","tripSeqNumber":null,"dutyCode":"150/T-F","firstStopName":"Sarangpur","lastStopName":"Sarangpur","busNo":0},{"ScheduleForRouteId":156,"schedulecode":"150/U","scheduleForRouteCode":"5693240","routeCode":"150-SC-U","routeName":"Sarangpur Darwaja - Chinubhainagar","routeDestination":"Chinubhainagar","routeVariant":"NORMAL","firstStopCode":1204,"lastStopCode":1819,"Shift":null,"startTime":"08:30:00","stopTime":"09:15:00","runCode":"150/U","tripSeqNumber":null,"dutyCode":"150/U-F","firstStopName":"Sarangpur","lastStopName":"Sarangpur","busNo":0},{"ScheduleForRouteId":211,"schedulecode":"150/V","scheduleForRouteCode":"5690719","routeCode":"150-SC-U","routeName":"Sarangpur Darwaja - Chinubhainagar","routeDestination":"Chinubhainagar","routeVariant":"NORMAL","firstStopCode":1204,"lastStopCode":1819,"Shift":null,"startTime":"08:50:00","stopTime":"09:35:00","runCode":"150/V","tripSeqNumber":null,"dutyCode":"150/V-F","firstStopName":"Sarangpur","lastStopName":"Sarangpur","busNo":0},{"ScheduleForRouteId":203,"schedulecode":"150/L","scheduleForRouteCode":"5690696","routeCode":"150-SC-U","routeName":"Sarangpur Darwaja - Chinubhainagar","routeDestination":"Chinubhainagar","routeVariant":"NORMAL","firstStopCode":1204,"lastStopCode":1819,"Shift":null,"startTime":"13:25:00","stopTime":"14:10:00","runCode":"150/L","tripSeqNumber":null,"dutyCode":"150/L-S","firstStopName":"Sarangpur","lastStopName":"Sarangpur","busNo":0},{"ScheduleForRouteId":204,"schedulecode":"150/M","scheduleForRouteCode":"5690704","routeCode":"150-SC-U","routeName":"Sarangpur Darwaja - Chinubhainagar","routeDestination":"Chinubhainagar","routeVariant":"NORMAL","firstStopCode":1204,"lastStopCode":1819,"Shift":null,"startTime":"13:45:00","stopTime":"14:30:00","runCode":"150/M","tripSeqNumber":null,"dutyCode":"150/M-S","firstStopName":"Sarangpur","lastStopName":"Sarangpur","busNo":0},{"ScheduleForRouteId":229,"schedulecode":"150/N","scheduleForRouteCode":"5690526","routeCode":"150-SC-U","routeName":"Sarangpur Darwaja - Chinubhainagar","routeDestination":"Chinubhainagar","routeVariant":"NORMAL","firstStopCode":1204,"lastStopCode":1819,"Shift":null,"startTime":"14:05:00","stopTime":"14:50:00","runCode":"150/N","tripSeqNumber":null,"dutyCode":"150/N-S","firstStopName":"Sarangpur","lastStopName":"Sarangpur","busNo":0},{"ScheduleForRouteId":210,"schedulecode":"150/O","scheduleForRouteCode":"5690710","routeCode":"150-SC-U","routeName":"Sarangpur Darwaja - Chinubhainagar","routeDestination":"Chinubhainagar","routeVariant":"NORMAL","firstStopCode":1204,"lastStopCode":1819,"Shift":null,"startTime":"14:25:00","stopTime":"15:10:00","runCode":"150/O","tripSeqNumber":null,"dutyCode":"150/O-S","firstStopName":"Sarangpur","lastStopName":"Sarangpur","busNo":0},{"ScheduleForRouteId":73,"schedulecode":"150/Z","scheduleForRouteCode":"5699168","routeCode":"150-SC-U","routeName":"Sarangpur Darwaja - Chinubhainagar","routeDestination":"Chinubhainagar","routeVariant":"NORMAL","firstStopCode":1204,"lastStopCode":1819,"Shift":null,"startTime":"14:35:00","stopTime":"15:15:00","runCode":"150/Z","tripSeqNumber":null,"dutyCode":"150/Z-S","firstStopName":"Sarangpur","lastStopName":"Sarangpur","busNo":0},{"ScheduleForRouteId":209,"schedulecode":"150/P","scheduleForRouteCode":"5690709","routeCode":"150-SC-U","routeName":"Sarangpur Darwaja - Chinubhainagar","routeDestination":"Chinubhainagar","routeVariant":"NORMAL","firstStopCode":1204,"lastStopCode":1819,"Shift":null,"startTime":"14:45:00","stopTime":"15:25:00","runCode":"150/P","tripSeqNumber":null,"dutyCode":"150/P-S","firstStopName":"Sarangpur","lastStopName":"Sarangpur","busNo":0},{"ScheduleForRouteId":226,"schedulecode":"150/Q","scheduleForRouteCode":"5690482","routeCode":"150-SC-U","routeName":"Sarangpur Darwaja - Chinubhainagar","routeDestination":"Chinubhainagar","routeVariant":"NORMAL","firstStopCode":1204,"lastStopCode":1819,"Shift":null,"startTime":"15:05:00","stopTime":"15:45:00","runCode":"150/Q","tripSeqNumber":null,"dutyCode":"150/Q-S","firstStopName":"Sarangpur","lastStopName":"Sarangpur","busNo":0},{"ScheduleForRouteId":72,"schedulecode":"150/Y","scheduleForRouteCode":"5699167","routeCode":"150-SC-U","routeName":"Sarangpur Darwaja - Chinubhainagar","routeDestination":"Chinubhainagar","routeVariant":"NORMAL","firstStopCode":1204,"lastStopCode":1819,"Shift":null,"startTime":"15:20:00","stopTime":"16:00:00","runCode":"150/Y","tripSeqNumber":null,"dutyCode":"150/Y-S","firstStopName":"Sarangpur","lastStopName":"Sarangpur","busNo":0},{"ScheduleForRouteId":205,"schedulecode":"150/R","scheduleForRouteCode":"5690705","routeCode":"150-SC-U","routeName":"Sarangpur Darwaja - Chinubhainagar","routeDestination":"Chinubhainagar","routeVariant":"NORMAL","firstStopCode":1204,"lastStopCode":1819,"Shift":null,"startTime":"15:30:00","stopTime":"16:10:00","runCode":"150/R","tripSeqNumber":null,"dutyCode":"150/R-S","firstStopName":"Sarangpur","lastStopName":"Sarangpur","busNo":0},{"ScheduleForRouteId":206,"schedulecode":"150/S","scheduleForRouteCode":"5690706","routeCode":"150-SC-U","routeName":"Sarangpur Darwaja - Chinubhainagar","routeDestination":"Chinubhainagar","routeVariant":"NORMAL","firstStopCode":1204,"lastStopCode":1819,"Shift":null,"startTime":"15:50:00","stopTime":"16:30:00","runCode":"150/S","tripSeqNumber":null,"dutyCode":"150/S-S","firstStopName":"Sarangpur","lastStopName":"Sarangpur","busNo":0},{"ScheduleForRouteId":207,"schedulecode":"150/T","scheduleForRouteCode":"5690707","routeCode":"150-SC-U","routeName":"Sarangpur Darwaja - Chinubhainagar","routeDestination":"Chinubhainagar","routeVariant":"NORMAL","firstStopCode":1204,"lastStopCode":1819,"Shift":null,"startTime":"16:05:00","stopTime":"16:45:00","runCode":"150/T","tripSeqNumber":null,"dutyCode":"150/T-S","firstStopName":"Sarangpur","lastStopName":"Sarangpur","busNo":0},{"ScheduleForRouteId":208,"schedulecode":"150/U","scheduleForRouteCode":"5690708","routeCode":"150-SC-U","routeName":"Sarangpur Darwaja - Chinubhainagar","routeDestination":"Chinubhainagar","routeVariant":"NORMAL","firstStopCode":1204,"lastStopCode":1819,"Shift":null,"startTime":"16:25:00","stopTime":"17:05:00","runCode":"150/U","tripSeqNumber":null,"dutyCode":"150/U-S","firstStopName":"Sarangpur","lastStopName":"Sarangpur","busNo":0},{"ScheduleForRouteId":69,"schedulecode":"150/X","scheduleForRouteCode":"5699143","routeCode":"150-SC-U","routeName":"Sarangpur Darwaja - Chinubhainagar","routeDestination":"Chinubhainagar","routeVariant":"NORMAL","firstStopCode":1204,"lastStopCode":1819,"Shift":null,"startTime":"16:35:00","stopTime":"17:25:00","runCode":"150/X","tripSeqNumber":null,"dutyCode":"150/X-S","firstStopName":"Sarangpur","lastStopName":"Sarangpur","busNo":0},{"ScheduleForRouteId":227,"schedulecode":"150/V","scheduleForRouteCode":"5690511","routeCode":"150-SC-U","routeName":"Sarangpur Darwaja - Chinubhainagar","routeDestination":"Chinubhainagar","routeVariant":"NORMAL","firstStopCode":1204,"lastStopCode":1819,"Shift":null,"startTime":"16:45:00","stopTime":"17:40:00","runCode":"150/V","tripSeqNumber":null,"dutyCode":"150/V-S","firstStopName":"Sarangpur","lastStopName":"Sarangpur","busNo":0}],"Paging":{"PageNo":0,"PageSize":2000,"PageCount":1,"TotalRecordCount":27}}