{"Data":[{"ScheduleForRouteId":1644,"schedulecode":"37/4/A","scheduleForRouteCode":"5697333","routeCode":"37/4-U","routeName":"Kalupur Terminus - But Bhavani Mandir","routeDestination":"But Bhavani Mandir","routeVariant":"NORMAL","firstStopCode":1715,"lastStopCode":1365,"Shift":null,"startTime":"05:55:00","stopTime":"06:40:00","runCode":"37/4/A","tripSeqNumber":null,"dutyCode":"37/4/A-F","firstStopName":"Kalupur Terminus","lastStopName":"Kalupur Terminus","busNo":0},{"ScheduleForRouteId":1645,"schedulecode":"37/4/A","scheduleForRouteCode":"5697335","routeCode":"37/4-U","routeName":"Kalupur Terminus - But Bhavani Mandir","routeDestination":"But Bhavani Mandir","routeVariant":"NORMAL","firstStopCode":1715,"lastStopCode":1365,"Shift":null,"startTime":"07:30:00","stopTime":"08:25:00","runCode":"37/4/A","tripSeqNumber":null,"dutyCode":"37/4/A-F","firstStopName":"Kalupur Terminus","lastStopName":"Kalupur Terminus","busNo":0},{"ScheduleForRouteId":1646,"schedulecode":"37/4/A","scheduleForRouteCode":"5697337","routeCode":"37/4-U","routeName":"Kalupur Terminus - But Bhavani Mandir","routeDestination":"But Bhavani Mandir","routeVariant":"NORMAL","firstStopCode":1715,"lastStopCode":1365,"Shift":null,"startTime":"09:20:00","stopTime":"10:15:00","runCode":"37/4/A","tripSeqNumber":null,"dutyCode":"37/4/A-F","firstStopName":"Kalupur Terminus","lastStopName":"Kalupur Terminus","busNo":0},{"ScheduleForRouteId":1647,"schedulecode":"37/4/A","scheduleForRouteCode":"5697339","routeCode":"37/4-U","routeName":"Kalupur Terminus - But Bhavani Mandir","routeDestination":"But Bhavani Mandir","routeVariant":"NORMAL","firstStopCode":1715,"lastStopCode":1365,"Shift":null,"startTime":"11:45:00","stopTime":"12:40:00","runCode":"37/4/A","tripSeqNumber":null,"dutyCode":"37/4/A-F","firstStopName":"Kalupur Terminus","lastStopName":"Kalupur Terminus","busNo":0},{"ScheduleForRouteId":1648,"schedulecode":"37/4/A","scheduleForRouteCode":"5697341","routeCode":"37/4-U","routeName":"Kalupur Terminus - But Bhavani Mandir","routeDestination":"But Bhavani Mandir","routeVariant":"NORMAL","firstStopCode":1715,"lastStopCode":1365,"Shift":null,"startTime":"14:00:00","stopTime":"14:50:00","runCode":"37/4/A","tripSeqNumber":null,"dutyCode":"37/4/A-S","firstStopName":"Kalupur Terminus","lastStopName":"Kalupur Terminus","busNo":0},{"ScheduleForRouteId":1690,"schedulecode":"37/4/A","scheduleForRouteCode":"5692403","routeCode":"37/4-U","routeName":"Kalupur Terminus - But Bhavani Mandir","routeDestination":"But Bhavani Mandir","routeVariant":"NORMAL","firstStopCode":1715,"lastStopCode":1365,"Shift":null,"startTime":"15:40:00","stopTime":"16:30:00","runCode":"37/4/A","tripSeqNumber":null,"dutyCode":"37/4/A-S","firstStopName":"Kalupur Terminus","lastStopName":"Kalupur Terminus","busNo":0},{"ScheduleForRouteId":1691,"schedulecode":"37/4/A","scheduleForRouteCode":"5692406","routeCode":"37/4-U","routeName":"Kalupur Terminus - But Bhavani Mandir","routeDestination":"But Bhavani Mandir","routeVariant":"NORMAL","firstStopCode":1715,"lastStopCode":1365,"Shift":null,"startTime":"18:00:00","stopTime":"18:55:00","runCode":"37/4/A","tripSeqNumber":null,"dutyCode":"37/4/A-S","firstStopName":"Kalupur Terminus","lastStopName":"Kalupur Terminus","busNo":0},{"ScheduleForRouteId":1683,"schedulecode":"37/4/A","scheduleForRouteCode":"5692523","routeCode":"37/4-U","routeName":"Kalupur Terminus - But Bhavani Mandir","routeDestination":"But Bhavani Mandir","routeVariant":"NORMAL","firstStopCode":1715,"lastStopCode":1365,"Shift":null,"startTime":"19:50:00","stopTime":"20:40:00","runCode":"37/4/A","tripSeqNumber":null,"dutyCode":"37/4/A-S","firstStopName":"Kalupur Terminus","lastStopName":"Kalupur Terminus","busNo":0}],"Paging":{"PageNo":0,"PageSize":2000,"PageCount":1,"TotalRecordCount":8}}