{"Data":[{"ScheduleForRouteId":698,"schedulecode":"64/3/A","scheduleForRouteCode":"5698013","routeCode":"64/3-U","routeName":"Lal Darwaja - Ranip Gam","routeDestination":"Ranip Gam","routeVariant":"NORMAL","firstStopCode":1125,"lastStopCode":3229,"Shift":null,"startTime":"08:15:00","stopTime":"09:00:00","runCode":"64/3/A","tripSeqNumber":null,"dutyCode":"64/3/A-G","firstStopName":"Lal Darwaja","lastStopName":"Lal Darwaja","busNo":0},{"ScheduleForRouteId":699,"schedulecode":"64/3/A","scheduleForRouteCode":"5698015","routeCode":"64/3-U","routeName":"Lal Darwaja - Ranip Gam","routeDestination":"Ranip Gam","routeVariant":"NORMAL","firstStopCode":1125,"lastStopCode":3229,"Shift":null,"startTime":"09:50:00","stopTime":"10:35:00","runCode":"64/3/A","tripSeqNumber":null,"dutyCode":"64/3/A-G","firstStopName":"Lal Darwaja","lastStopName":"Lal Darwaja","busNo":0},{"ScheduleForRouteId":700,"schedulecode":"64/3/A","scheduleForRouteCode":"5698017","routeCode":"64/3-U","routeName":"Lal Darwaja - Ranip Gam","routeDestination":"Ranip Gam","routeVariant":"NORMAL","firstStopCode":1125,"lastStopCode":3229,"Shift":null,"startTime":"11:25:00","stopTime":"12:15:00","runCode":"64/3/A","tripSeqNumber":null,"dutyCode":"64/3/A-G","firstStopName":"Lal Darwaja","lastStopName":"Lal Darwaja","busNo":0},{"ScheduleForRouteId":701,"schedulecode":"64/3/A","scheduleForRouteCode":"5698019","routeCode":"64/3-U","routeName":"Lal Darwaja - Ranip Gam","routeDestination":"Ranip Gam","routeVariant":"NORMAL","firstStopCode":1125,"lastStopCode":3229,"Shift":null,"startTime":"14:10:00","stopTime":"15:00:00","runCode":"64/3/A","tripSeqNumber":null,"dutyCode":"64/3/A-G","firstStopName":"Lal Darwaja","lastStopName":"Lal Darwaja","busNo":0},{"ScheduleForRouteId":702,"schedulecode":"64/3/A","scheduleForRouteCode":"5698021","routeCode":"64/3-U","routeName":"Lal Darwaja - Ranip Gam","routeDestination":"Ranip Gam","routeVariant":"NORMAL","firstStopCode":1125,"lastStopCode":3229,"Shift":null,"startTime":"15:50:00","stopTime":"16:40:00","runCode":"64/3/A","tripSeqNumber":null,"dutyCode":"64/3/A-G","firstStopName":"Lal Darwaja","lastStopName":"Lal Darwaja","busNo":0},{"ScheduleForRouteId":703,"schedulecode":"64/3/A","scheduleForRouteCode":"5698023","routeCode":"64/3-U","routeName":"Lal Darwaja - Ranip Gam","routeDestination":"Ranip Gam","routeVariant":"NORMAL","firstStopCode":1125,"lastStopCode":3229,"Shift":null,"startTime":"17:30:00","stopTime":"18:20:00","runCode":"64/3/A","tripSeqNumber":null,"dutyCode":"64/3/A-G","firstStopName":"Lal Darwaja","lastStopName":"Lal Darwaja","busNo":0},{"ScheduleForRouteId":704,"schedulecode":"64/3/A","scheduleForRouteCode":"5698025","routeCode":"64/3-U","routeName":"Lal Darwaja - Ranip Gam","routeDestination":"Ranip Gam","routeVariant":"NORMAL","firstStopCode":1125,"lastStopCode":3229,"Shift":null,"startTime":"19:15:00","stopTime":"20:10:00","runCode":"64/3/A","tripSeqNumber":null,"dutyCode":"64/3/A-G","firstStopName":"Lal Darwaja","lastStopName":"Lal Darwaja","busNo":0}],"Paging":{"PageNo":0,"PageSize":2000,"PageCount":1,"TotalRecordCount":7}}