{"Data":[{"ScheduleForRouteId":8698,"schedulecode":"69/A","scheduleForRouteCode":"5692756","routeCode":"69-SP(S)U-D","routeName":"Oganaj Circle (S.P.Ring Road) - Kalupur Terminus","routeDestination":"Kalupur Terminus","routeVariant":"NORMAL","firstStopCode":8867,"lastStopCode":1734,"Shift":null,"startTime":"20:00:00","stopTime":"21:10:00","runCode":"69/A","tripSeqNumber":null,"dutyCode":"69/A-G","firstStopName":"Oganaj Circle (S.P.Ring Road)","lastStopName":"Oganaj Circle (S.P.Ring Road)","busNo":0}],"Paging":{"PageNo":0,"PageSize":2000,"PageCount":1,"TotalRecordCount":1}}