{"Data":[{"ScheduleForRouteId":2335,"schedulecode":"F5/A","scheduleForRouteCode":"5694694","routeCode":"Feeder/5-SaS-U","routeName":"Sarangpur - Shardaben Hospital","routeDestination":"Shardaben Hospital","routeVariant":"NORMAL","firstStopCode":2270,"lastStopCode":3438,"Shift":null,"startTime":"14:15:00","stopTime":"14:30:00","runCode":"F5/A","tripSeqNumber":null,"dutyCode":"F5/A-S","firstStopName":"Sarangpur","lastStopName":"Sarangpur","busNo":0}],"Paging":{"PageNo":0,"PageSize":2000,"PageCount":1,"TotalRecordCount":1}}