{"Data":[{"ScheduleForRouteId":917,"schedulecode":"17/SN02","scheduleForRouteCode":"5829762","routeCode":"17E","routeName":"Nehrunagar - Jaimangal","routeDestination":"Jaimangal","routeVariant":"NORMAL","firstStopCode":32,"lastStopCode":14,"Shift":null,"startTime":"12:21:00","stopTime":"12:37:00","runCode":"17/SN02","tripSeqNumber":null,"dutyCode":null,"firstStopName":"Nehrunagar","lastStopName":"Nehrunagar","busNo":1},{"ScheduleForRouteId":924,"schedulecode":"17/SN03","scheduleForRouteCode":"5829775","routeCode":"17E","routeName":"Nehrunagar - Jaimangal","routeDestination":"Jaimangal","routeVariant":"NORMAL","firstStopCode":32,"lastStopCode":14,"Shift":null,"startTime":"12:41:00","stopTime":"12:57:00","runCode":"17/SN03","tripSeqNumber":null,"dutyCode":null,"firstStopName":"Nehrunagar","lastStopName":"Nehrunagar","busNo":2},{"ScheduleForRouteId":937,"schedulecode":"17/NS01","scheduleForRouteCode":"5829798","routeCode":"17E","routeName":"Nehrunagar - Jaimangal","routeDestination":"Jaimangal","routeVariant":"NORMAL","firstStopCode":32,"lastStopCode":14,"Shift":null,"startTime":"13:03:00","stopTime":"13:19:00","runCode":"17/NS01","tripSeqNumber":null,"dutyCode":null,"firstStopName":"Nehrunagar","lastStopName":"Nehrunagar","busNo":3},{"ScheduleForRouteId":939,"schedulecode":"17/SN04","scheduleForRouteCode":"5829801","routeCode":"17E","routeName":"Nehrunagar - Jaimangal","routeDestination":"Jaimangal","routeVariant":"NORMAL","firstStopCode":32,"lastStopCode":14,"Shift":null,"startTime":"14:02:00","stopTime":"14:18:00","runCode":"17/SN04","tripSeqNumber":null,"dutyCode":null,"firstStopName":"Nehrunagar","lastStopName":"Nehrunagar","busNo":4},{"ScheduleForRouteId":943,"schedulecode":"17/NS04","scheduleForRouteCode":"5829816","routeCode":"17E","routeName":"Nehrunagar - Jaimangal","routeDestination":"Jaimangal","routeVariant":"NORMAL","firstStopCode":32,"lastStopCode":14,"Shift":null,"startTime":"15:07:00","stopTime":"15:23:00","runCode":"17/NS04","tripSeqNumber":null,"dutyCode":null,"firstStopName":"Nehrunagar","lastStopName":"Nehrunagar","busNo":5},{"ScheduleForRouteId":944,"schedulecode":"17/NS06","scheduleForRouteCode":"5829817","routeCode":"17E","routeName":"Nehrunagar - Jaimangal","routeDestination":"Jaimangal","routeVariant":"NORMAL","firstStopCode":32,"lastStopCode":14,"Shift":null,"startTime":"15:27:00","stopTime":"15:43:00","runCode":"17/NS06","tripSeqNumber":null,"dutyCode":null,"firstStopName":"Nehrunagar","lastStopName":"Nehrunagar","busNo":6},{"ScheduleForRouteId":965,"schedulecode":"17/NS07","scheduleForRouteCode":"5829851","routeCode":"17E","routeName":"Nehrunagar - Jaimangal","routeDestination":"Jaimangal","routeVariant":"NORMAL","firstStopCode":32,"lastStopCode":14,"Shift":null,"startTime":"15:46:00","stopTime":"16:02:00","runCode":"17/NS07","tripSeqNumber":null,"dutyCode":null,"firstStopName":"Nehrunagar","lastStopName":"Nehrunagar","busNo":7}],"Paging":{"PageNo":0,"PageSize":2000,"PageCount":1,"TotalRecordCount":7}}